articleformater/Abbrv.py
articleformater/TeXanalyser.py
articleformater/__init__.py
articleformater/bibformat.py
articleformater/menu.py
articleformater/menu_unix.py
articleformater/pickle.obj
articleformater/wbibformat.py
bibtex_format_rita-0.1.1.data/scripts/Abbrv.py
bibtex_format_rita-0.1.1.data/scripts/TeXanalyser.py
bibtex_format_rita-0.1.1.data/scripts/bibformat.py
bibtex_format_rita-0.1.1.data/scripts/wbibformat.py
bibtex_format_rita-0.1.1.dist-info/LICENSE.md
bibtex_format_rita-0.1.1.dist-info/METADATA
bibtex_format_rita-0.1.1.dist-info/WHEEL
bibtex_format_rita-0.1.1.dist-info/dependency_links.txt
bibtex_format_rita-0.1.1.dist-info/top_level.txt
bibtex_format_rita-0.1.1.dist-info/RECORD
