Metadata-Version: 2.1
Name: bibtex-format-rita
Version: 0.1.1
Summary: Implements simple bibtex bibliography file formating functions
Home-page: https://github.com/mlcruz/TeXArticleFormater
Author: Matheus Cruz
Author-email: mlcruz@inf.ufrgs.br
License: UNKNOWN
Platform: UNKNOWN
Classifier: Programming Language :: Python :: 3
Classifier: License :: OSI Approved :: MIT License
Classifier: Operating System :: OS Independent
Requires-Dist: regex
Requires-Dist: click
Requires-Dist: requests
Requires-Dist: colorama
Requires-Dist: easygui
